{
  "ticker": "PRB",
  "name": "Probe Gold Inc.",
  "exchange": "TSX",
  "website": "https://probegold.com",
  "primary_commodity": "Gold",
  "jurisdiction": "Quebec, Canada",
  "description": "Probe Gold Inc. was a gold exploration and development company focused on the Novador property in Val-d'Or, Quebec, hosting 3.79 million ounces of Measured and Indicated gold resources across the Monique, Pascalis, and Courvan trends. The company was acquired by Fresnillo plc for approximately C$780 million in January 2026."
}
