{
  "ticker": "SKE",
  "name": "Skeena Resources Limited",
  "exchange": "TSX",
  "website": "https://skeenagoldsilver.com",
  "primary_commodity": "Gold",
  "jurisdiction": "British Columbia, Canada",
  "description": "Skeena Resources Limited is an advanced-stage gold-silver developer focused on the Eskay Creek project in British Columbia's Golden Triangle, covering approximately 7,666 hectares. The company received its Environmental Management Act Permit in February 2026 and is targeting production in 2027, with a market capitalization of approximately C$4.5 billion."
}
